binary_lif_neuron.v
// binary_lif_neuron.v
`timescale 1ns / 1ps

// Module: binary_lif_neuron
// Description: Implements a binary Leaky Integrate-and-Fire (LIF) neuron.
//              The neuron's potential (P) accumulates input (I) and leaks over time
//              based on a leak factor (lambda). If the potential exceeds a threshold (theta),
//              the neuron spikes (S=1) and its potential is reset.
//
// Parameters:
//   POTENTIAL_WIDTH: Width of the register for the potential variable P.
//                    This determines the maximum integer value P can hold.
//   FRACTION_BITS:   Number of bits representing the fractional part in fixed-point
//                    arithmetic. This allows for representing values like 0.5 or 0.9.
//                    The actual scale factor is 2^FRACTION_BITS.
//
// Inputs:
//   clk:               System clock. Operations occur on its positive edge.
//   reset:             Asynchronous reset signal. When high, clears P and S.
//   I:                 Binary input to the neuron (0 or 1).
//   lambda_val_scaled: Scaled leak factor (lambda * 2^FRACTION_BITS).
//                      Lambda is between 0 and 1.
//   theta_val_scaled:  Scaled threshold value (theta * 2^FRACTION_BITS).
//   reset_val_scaled:  Scaled potential value to reset P to after a spike
//                      (reset_val * 2^FRACTION_BITS).
//
// Outputs:
//   S:                 Spiking state of the neuron (0 for not spiking, 1 for spiking).

module binary_lif_neuron #(
    parameter POTENTIAL_WIDTH = 16, // Width for the potential variable P (e.g., 16 bits)
    parameter FRACTION_BITS = 8     // Number of bits for the fractional part (e.g., 8 bits for 256 scale)
) (
    input wire clk,
    input wire reset,
    input wire I,                   // Binary input (0 or 1)
    input wire [FRACTION_BITS-1:0] lambda_val_scaled, // Leak factor, scaled (e.g., 0.8 -> 204 if FRACTION_BITS=8)
    input wire [POTENTIAL_WIDTH-1:0] theta_val_scaled,  // Threshold, scaled (e.g., 1.5 -> 384 if FRACTION_BITS=8)
    input wire [POTENTIAL_WIDTH-1:0] reset_val_scaled,  // Reset potential, scaled (e.g., 0.1 -> 25 if FRACTION_BITS=8)
    output reg S                     // Spiking state (0 or 1)
);

    // Register to store the neuron's potential.
    // Its width includes both integer and fractional parts as defined by POTENTIAL_WIDTH.
    reg [POTENTIAL_WIDTH-1:0] P;

    // Initial block for simulation setup.
    // In a real hardware design (FPGA/ASIC), P and S would typically be initialized
    // by a power-on reset or through the 'reset' signal. This block ensures defined
    // states at time 0 for Verilog simulation environments.
    initial begin
        P = 0; // Initialize potential to zero
        S = 0; // Initialize spike state to zero
    end

    // Always block for sequential logic, triggered by clock positive edge or reset positive edge.
    always @(posedge clk or posedge reset) begin
        if (reset) begin
            // Asynchronous reset:
            // When 'reset' is high, immediately clear the potential and spike state.
            P <= 0;
            S <= 0;
        end else begin
            // Non-reset state (normal operation):
            // 1. Calculate the leaked potential: P(t-1) * lambda
            //    The multiplication result can be wider than POTENTIAL_WIDTH + FRACTION_BITS.
            //    It's temporarily stored in 'P_mul_result'.
            //    The right shift (>>>) by FRACTION_BITS effectively divides by 2^FRACTION_BITS,
            //    performing the fixed-point scaling operation for the leak.
            reg [POTENTIAL_WIDTH + FRACTION_BITS - 1:0] P_mul_result;
            reg [POTENTIAL_WIDTH-1:0] P_current_cycle_calc; // Potential value calculated for this cycle

            P_mul_result = P * lambda_val_scaled;
            P_current_cycle_calc = P_mul_result >>> FRACTION_BITS;

            // 2. Accumulate input: Add the scaled input I(t) to the leaked potential.
            //    If I is 1, we add 2^FRACTION_BITS, which represents 1.0 in our fixed-point format.
            //    If I is 0, nothing is added.
            P_current_cycle_calc = P_current_cycle_calc + (I ? (1 << FRACTION_BITS) : 0);

            // 3. Threshold function and Reset mechanism:
            //    Check if the newly calculated potential exceeds or meets the threshold.
            if (P_current_cycle_calc >= theta_val_scaled) begin
                // If potential crosses threshold:
                S <= 1;             // Neuron spikes (output S becomes 1)
                P <= reset_val_scaled; // Reset potential to the specified reset_val_scaled
            end else begin
                // If potential does not cross threshold:
                S <= 0;             // Neuron does not spike (output S remains 0)
                P <= P_current_cycle_calc; // Update potential with the calculated value
            end
        end
    end

endmodule

tb_binary_lif_neuron.v
// tb_binary_lif_neuron.v
`timescale 1ns / 1ps

// Module: tb_binary_lif_neuron
// Description: Testbench for the binary_lif_neuron module.
//              This testbench provides clock, reset, and various input scenarios
//              to verify the functionality of the LIF neuron.
//              It also dumps waveforms to a VCD file for visual inspection.
module tb_binary_lif_neuron;

    // Parameters for the LIF neuron under test.
    // These must match the parameters defined in the 'binary_lif_neuron' module.
    parameter POTENTIAL_WIDTH = 16;      // Width of the potential variable (P)
    parameter FRACTION_BITS = 8;         // Number of bits for the fractional part
    parameter SCALE_FACTOR = (1 << FRACTION_BITS); // Calculation of 2^FRACTION_BITS (e.g., 256)

    // Testbench signals (registers for inputs, wires for outputs)
    reg clk;
    reg reset;
    reg I; // Binary input to the neuron
    reg [FRACTION_BITS-1:0] lambda_val_scaled; // Scaled leak factor
    reg [POTENTIAL_WIDTH-1:0] theta_val_scaled;  // Scaled threshold
    reg [POTENTIAL_WIDTH-1:0] reset_val_scaled;  // Scaled reset potential
    wire S; // Spiking output from the neuron

    // Clock generation: Creates a periodic clock signal.
    // The clock period is defined by CLK_PERIOD.
    parameter CLK_PERIOD = 10; // 10 ns clock period (corresponds to 100 MHz clock frequency)
    always #((CLK_PERIOD / 2)) clk = ~clk; // Toggle clock every half period

    // Instantiate the Binary LIF Neuron module under test.
    // Parameters are passed to configure the neuron's width and fixed-point precision.
    binary_lif_neuron #(
        .POTENTIAL_WIDTH(POTENTIAL_WIDTH),
        .FRACTION_BITS(FRACTION_BITS)
    ) lif_neuron (
        .clk(clk),
        .reset(reset),
        .I(I),
        .lambda_val_scaled(lambda_val_scaled),
        .theta_val_scaled(theta_val_scaled),
        .reset_val_scaled(reset_val_scaled),
        .S(S)
    );

    // Initial block for defining test scenarios and simulation control.
    initial begin
        // Setup VCD (Value Change Dump) file for waveform visualization.
        // This allows you to view signal changes over time using tools like GTKWave.
        $dumpfile("lif_neuron.vcd");    // Specifies the output VCD file name
        $dumpvars(0, tb_binary_lif_neuron); // Dumps all signals in the current scope to the VCD file

        // 1. Initialize all testbench signals to a known state.
        clk = 0;
        reset = 1; // Assert reset initially to clear the neuron's state
        I = 0;
        lambda_val_scaled = 0;
        theta_val_scaled = 0;
        reset_val_scaled = 0;

        // Apply reset for one full clock cycle to ensure the neuron initializes correctly.
        #CLK_PERIOD; // Wait for one clock period while reset is active
        reset = 0;   // De-assert reset to begin normal operation

        $display("--- Starting Simulation ---");

        // --- Scenario 1: Constant input below threshold ---
        // Objective: Demonstrate that the neuron does not spike if the input is
        //            insufficient to raise the potential above the threshold,
        //            especially with significant leakage.
        $display("\nScenario 1: Constant input below threshold");
        // Parameters for this scenario:
        //   lambda = 0.5 (high leakage) -> 0.5 * 256 = 128
        //   theta  = 2.0 (high threshold) -> 2.0 * 256 = 512
        //   reset_val = 0.0 (reset to zero after spike, though not expected here)
        lambda_val_scaled = 0.5 * SCALE_FACTOR; // Leak factor (0.5)
        theta_val_scaled = 2.0 * SCALE_FACTOR;  // High threshold (2.0)
        reset_val_scaled = 0.0 * SCALE_FACTOR;  // Reset potential (0.0)
        I = 1; // Provide a constant input pulse

        repeat (20) @(posedge clk); // Run for 20 clock cycles to observe behavior
        $display("Expected S1: Potential should accumulate but not reach threshold. S should remain 0.");


        // --- Scenario 2: Input that accumulates until reaching threshold ---
        // Objective: Show that the neuron's potential can build up over time with
        //            repeated inputs, eventually crossing the threshold and spiking.
        $display("\nScenario 2: Input accumulates until reaching threshold");
        // Reset the neuron state before starting a new scenario.
        reset = 1; #CLK_PERIOD; reset = 0;
        // Parameters for this scenario:
        //   lambda = 0.9 (less leakage) -> 0.9 * 256 = 230 (approx)
        //   theta  = 1.5 (moderate threshold) -> 1.5 * 256 = 384
        //   reset_val = 0.1 (reset to a small positive value after spike)
        lambda_val_scaled = 0.9 * SCALE_FACTOR; // Leak factor (0.9)
        theta_val_scaled = 1.5 * SCALE_FACTOR;  // Moderate threshold (1.5)
        reset_val_scaled = 0.1 * SCALE_FACTOR;  // Reset potential (0.1)
        I = 1; // Provide a constant input pulse

        repeat (20) @(posedge clk); // Run for 20 clock cycles
        $display("Expected S2: Potential should accumulate and eventually reach threshold, causing spikes.");


        // --- Scenario 3: Leakage with no input ---
        // Objective: Demonstrate the leakage mechanism where the potential decays
        //            when no input is present.
        $display("\nScenario 3: Leakage with no input");
        // Reset the neuron state.
        reset = 1; #CLK_PERIOD; reset = 0;
        // Parameters for this scenario:
        //   lambda = 0.8 (moderate leakage) -> 0.8 * 256 = 204 (approx)
        //   theta  = 1.0 (threshold 1.0)
        //   reset_val = 0.0
        lambda_val_scaled = 0.8 * SCALE_FACTOR; // Leak factor (0.8)
        theta_val_scaled = 1.0 * SCALE_FACTOR;  // Threshold (1.0)
        reset_val_scaled = 0.0 * SCALE_FACTOR;  // Reset potential (0.0)

        // First, provide some input to build up the potential to a non-zero value.
        I = 1;
        repeat (5) @(posedge clk); // Apply input for 5 cycles
        I = 0; // Then, remove the input to observe pure leakage

        repeat (20) @(posedge clk); // Run for 20 clock cycles to observe leakage
        $display("Expected S3: Potential should decrease over time due to leakage.");


        // --- Scenario 4: Strong input causing immediate spiking ---
        // Objective: Show that a sufficiently strong input (or low threshold) can
        //            cause the neuron to spike quickly, potentially in a single cycle.
        $display("\nScenario 4: Strong input causing immediate spiking");
        // Reset the neuron state.
        reset = 1; #CLK_PERIOD; reset = 0;
        // Parameters for this scenario:
        //   lambda = 0.8 (moderate leakage)
        //   theta  = 0.5 (very low threshold) -> 0.5 * 256 = 128
        //   reset_val = 0.0
        lambda_val_scaled = 0.8 * SCALE_FACTOR; // Leak factor (0.8)
        theta_val_scaled = 0.5 * SCALE_FACTOR;  // Very low threshold (0.5)
        reset_val_scaled = 0.0 * SCALE_FACTOR;  // Reset potential (0.0)

        I = 1; // Provide a strong input, expected to cause immediate spiking

        repeat (10) @(posedge clk); // Run for 10 clock cycles
        $display("Expected S4: Neuron should spike almost immediately with strong input.");


        // Small delay before finishing simulation to ensure final state is captured.
        #CLK_PERIOD;
        $display("\n--- Simulation Finished ---");
        $finish; // End the simulation
    end

    // Monitor block: Displays the current state of important signals at each positive clock edge.
    // This helps in understanding the neuron's behavior during simulation.
    // The potential 'P' is also displayed in its scaled (integer) and unscaled (float) forms.
    always @(posedge clk) begin
        $display("Time: %0t ns, Reset: %b, Input I: %b, P: %0d (%.3f), S: %b",
                 $time, reset, I, lif_neuron.P, $itor(lif_neuron.P) / SCALE_FACTOR, S);
    end

endmodule

lif_neuron.vcd
$date
	Sun Jun 15 02:15:34 2025
$end
$version
	Icarus Verilog
$end
$timescale
	1ps
$end
$scope module tb_binary_lif_neuron $end
$var wire 1 ! S $end
$var parameter 32 " CLK_PERIOD $end
$var parameter 32 # FRACTION_BITS $end
$var parameter 32 $ POTENTIAL_WIDTH $end
$var parameter 40 % SCALE_FACTOR $end
$var reg 1 & I $end
$var reg 1 ' clk $end
$var reg 8 ( lambda_val_scaled [7:0] $end
$var reg 1 ) reset $end
$var reg 16 * reset_val_scaled [15:0] $end
$var reg 16 + theta_val_scaled [15:0] $end
$scope module lif_neuron $end
$var wire 1 & I $end
$var wire 1 ' clk $end
$var wire 8 , lambda_val_scaled [7:0] $end
$var wire 1 ) reset $end
$var wire 16 - reset_val_scaled [15:0] $end
$var wire 16 . theta_val_scaled [15:0] $end
$var parameter 32 / FRACTION_BITS $end
$var parameter 32 0 POTENTIAL_WIDTH $end
$var reg 16 1 P [15:0] $end
$var reg 1 ! S $end
$scope begin $unm_blk_6 $end
$var reg 16 2 P_current_cycle_calc [15:0] $end
$var reg 24 3 P_mul_result [23:0] $end
$upscope $end
$upscope $end
$upscope $end
$enddefinitions $end
$comment Show the parameter values. $end
$dumpall
b10000 0
b1000 /
b100000000 %
b10000 $
b1000 #
b1010 "
$end
#0
$dumpvars
bx 3
bx 2
b0 1
b0 .
b0 -
b0 ,
b0 +
b0 *
1)
b0 (
0'
0&
0!
$end
#5000
1'
#10000
0'
1&
b1000000000 +
b1000000000 .
b10000000 (
b10000000 ,
0)
#15000
b100000000 1
b100000000 2
b0 3
1'
#20000
0'
#25000
b110000000 1
b110000000 2
b1000000000000000 3
1'
#30000
0'
#35000
b111000000 1
b111000000 2
b1100000000000000 3
1'
#40000
0'
#45000
b111100000 1
b111100000 2
b1110000000000000 3
1'
#50000
0'
#55000
b111110000 1
b111110000 2
b1111000000000000 3
1'
#60000
0'
#65000
b111111000 1
b111111000 2
b1111100000000000 3
1'
#70000
0'
#75000
b111111100 1
b111111100 2
b1111110000000000 3
1'
#80000
0'
#85000
b111111110 1
b111111110 2
b1111111000000000 3
1'
#90000
0'
#95000
b111111111 1
b111111111 2
b1111111100000000 3
1'
#100000
0'
#105000
b111111111 2
b1111111110000000 3
1'
#110000
0'
#115000
b111111111 2
1'
#120000
0'
#125000
b111111111 2
1'
#130000
0'
#135000
b111111111 2
1'
#140000
0'
#145000
b111111111 2
1'
#150000
0'
#155000
b111111111 2
1'
#160000
0'
#165000
b111111111 2
1'
#170000
0'
#175000
b111111111 2
1'
#180000
0'
#185000
b111111111 2
1'
#190000
0'
#195000
b111111111 2
1'
#200000
0'
#205000
b0 1
1)
1'
#210000
0'
#215000
b100000000 1
b100000000 2
b0 3
1'
b11010 *
b11010 -
b110000000 +
b110000000 .
b11100110 (
b11100110 ,
0)
#220000
0'
#225000
b11010 1
1!
b111100110 2
b1110011000000000 3
1'
#230000
0'
#235000
b100010111 1
0!
b100010111 2
b1011101011100 3
1'
#240000
0'
#245000
b11010 1
1!
b111111010 2
b1111101010101010 3
1'
#250000
0'
#255000
b100010111 1
0!
b100010111 2
b1011101011100 3
1'
#260000
0'
#265000
b11010 1
1!
b111111010 2
b1111101010101010 3
1'
#270000
0'
#275000
b100010111 1
0!
b100010111 2
b1011101011100 3
1'
#280000
0'
#285000
b11010 1
1!
b111111010 2
b1111101010101010 3
1'
#290000
0'
#295000
b100010111 1
0!
b100010111 2
b1011101011100 3
1'
#300000
0'
#305000
b11010 1
1!
b111111010 2
b1111101010101010 3
1'
#310000
0'
#315000
b100010111 1
0!
b100010111 2
b1011101011100 3
1'
#320000
0'
#325000
b11010 1
1!
b111111010 2
b1111101010101010 3
1'
#330000
0'
#335000
b100010111 1
0!
b100010111 2
b1011101011100 3
1'
#340000
0'
#345000
b11010 1
1!
b111111010 2
b1111101010101010 3
1'
#350000
0'
#355000
b100010111 1
0!
b100010111 2
b1011101011100 3
1'
#360000
0'
#365000
b11010 1
1!
b111111010 2
b1111101010101010 3
1'
#370000
0'
#375000
b100010111 1
0!
b100010111 2
b1011101011100 3
1'
#380000
0'
#385000
b11010 1
1!
b111111010 2
b1111101010101010 3
1'
#390000
0'
#395000
b100010111 1
0!
b100010111 2
b1011101011100 3
1'
#400000
0'
#405000
b0 1
1)
1'
#410000
0'
#415000
1!
b100000000 2
b0 3
1'
b0 *
b0 -
b100000000 +
b100000000 .
b11001101 (
b11001101 ,
0)
#420000
0'
#425000
b100000000 2
1'
#430000
0'
#435000
b100000000 2
1'
#440000
0'
#445000
b100000000 2
1'
#450000
0'
#455000
0!
b0 2
0&
1'
#460000
0'
#465000
1'
#470000
0'
#475000
1'
#480000
0'
#485000
1'
#490000
0'
#495000
1'
#500000
0'
#505000
1'
#510000
0'
#515000
1'
#520000
0'
#525000
1'
#530000
0'
#535000
1'
#540000
0'
#545000
1'
#550000
0'
#555000
1'
#560000
0'
#565000
1'
#570000
0'
#575000
1'
#580000
0'
#585000
1'
#590000
0'
#595000
1'
#600000
0'
#605000
1'
#610000
0'
#615000
1'
#620000
0'
#625000
1'
#630000
0'
#635000
1'
#640000
0'
#645000
1'
#650000
0'
#655000
1)
1'
#660000
0'
#665000
1!
b100000000 2
1'
1&
b10000000 +
b10000000 .
0)
#670000
0'
#675000
b100000000 2
1'
#680000
0'
#685000
b100000000 2
1'
#690000
0'
#695000
b100000000 2
1'
#700000
0'
#705000
b100000000 2
1'
#710000
0'
#715000
b100000000 2
1'
#720000
0'
#725000
b100000000 2
1'
#730000
0'
#735000
b100000000 2
1'
#740000
0'
#745000
b100000000 2
1'
#750000
0'
#755000
b100000000 2
1'
#760000
0'
#765000
b100000000 2
1'
